{
  "observed": 320.45585253462195,
  "expected": 356.7298197678756,
  "difference": -0.10168470708968806,
  "max_bin_difference": 1.7306075667531067,
  "max_bin_difference_bin": 13,
  "max_bin_difference_filtered": 0.6491510938133176,
  "max_bin_difference_filtered_bin": 137,
  "snr_threshold": 3.0,
  "mass_range_min": 10.0,
  "mass_range_max": 160.0,
  "percentile_68_difference": 0.1799995183313116,
  "percentile_95_difference": 0.4297493526854211,
  "rms_bin_difference": 0.19802987926606685,
  "chi2": 47.76807133446152,
  "ndf": 58,
  "chi2_per_ndf": 0.8235874368010606,
  "p_value": 0.8288245058117589,
  "closure_uncertainty_scale": 0.65,
  "recommended_systematic_pct": 35.0
}