{
  "observed": 53.48215986043215,
  "expected": 60.24965106451418,
  "difference": -0.1123241559828377,
  "max_bin_difference": 0.36353937765758504,
  "max_bin_difference_bin": 1,
  "max_bin_difference_filtered": 0.36353937765758504,
  "max_bin_difference_filtered_bin": 1,
  "snr_threshold": 3.0,
  "mass_range_min": 10.0,
  "mass_range_max": 160.0,
  "percentile_68_difference": 0.17705283773589564,
  "percentile_95_difference": 0.3352116456746924,
  "rms_bin_difference": 0.18744727265511443,
  "chi2": 17.924294468039296,
  "ndf": 11,
  "chi2_per_ndf": 1.6294813152762997,
  "p_value": 0.08335395488085685,
  "closure_uncertainty_scale": 1.7000000000000002,
  "recommended_systematic_pct": 70.00000000000001
}