{
  "syst": "cjet",
  "observed": 61.670116206631064,
  "expected": 121.74784921132232,
  "difference": -0.49346032306831206,
  "max_bin_difference": 11.706467506163012,
  "max_bin_difference_bin": 122,
  "max_bin_difference_filtered": 1.287114974698545,
  "max_bin_difference_filtered_bin": 53,
  "snr_threshold": 3.0,
  "mass_range_min": 10.0,
  "mass_range_max": 160.0,
  "percentile_68_difference": 0.6512246277133246,
  "percentile_95_difference": 1.1015841666848865,
  "rms_bin_difference": 0.6182979105589893,
  "chi2": 68.98502499123641,
  "ndf": 19,
  "chi2_per_ndf": 3.6307907890124427,
  "p_value": 1.3553734346069784e-07,
  "closure_uncertainty_scale": 2.0500000000000003,
  "recommended_systematic_pct": 105.00000000000003
}